IntInput/INIP.py
IntInput/__init__.py
intinput-1.3.0.dist-info/METADATA
intinput-1.3.0.dist-info/WHEEL
intinput-1.3.0.dist-info/top_level.txt
intinput-1.3.0.dist-info/RECORD
