Metadata-Version: 2.1
Name: intinput
Version: 1.3.0
Summary: A intput function that only reads intergers
Home-page: https://github.com/Sisigoks/IntInput_Module
Author: Sibi Gokul
Author-email: Sisi.goks2008@gmail.com
